MANIFEST.in
README.rst
setup.py
src/AUTHORS.txt
src/HISTORY.txt
src/README.txt
src/sphinxjp/__init__.py
src/sphinxjp.themes.tinkerbelizehole.egg-info/PKG-INFO
src/sphinxjp.themes.tinkerbelizehole.egg-info/SOURCES.txt
src/sphinxjp.themes.tinkerbelizehole.egg-info/dependency_links.txt
src/sphinxjp.themes.tinkerbelizehole.egg-info/entry_points.txt
src/sphinxjp.themes.tinkerbelizehole.egg-info/namespace_packages.txt
src/sphinxjp.themes.tinkerbelizehole.egg-info/not-zip-safe
src/sphinxjp.themes.tinkerbelizehole.egg-info/requires.txt
src/sphinxjp.themes.tinkerbelizehole.egg-info/top_level.txt
src/sphinxjp/themes/__init__.py
src/sphinxjp/themes/tinkerbelizehole/__init__.py
src/sphinxjp/themes/tinkerbelizehole/templates/tinkerbelizehole/layout.html
src/sphinxjp/themes/tinkerbelizehole/templates/tinkerbelizehole/theme.conf
src/sphinxjp/themes/tinkerbelizehole/templates/tinkerbelizehole/static/pygments.css
src/sphinxjp/themes/tinkerbelizehole/templates/tinkerbelizehole/static/tinkerbelizehole.css_t