Metadata-Version: 1.1
Name: sphinxjp.themes.tinkerbelizehole
Version: 0.2.0
Summary: A single column blogging theme tool for Tinkerer, based on belizehole color.
Home-page: https://github.com/naoiwata/sphinxjp.themes.tinkerbelizehole
Author: nao iwata
Author-email: orrrizzle{at}gmail.com
License: MIT
Keywords: tinkerer,sphinxjp,reStructuredText,theme
Platform: UNKNOWN
Classifier: Development Status :: 4 - Beta
Classifier: License :: OSI Approved :: MIT License
Classifier: Programming Language :: Python
Classifier: Topic :: Software Development
Classifier: Topic :: Software Development :: Documentation
Classifier: Topic :: Text Processing :: Markup
